[
    {
        "key": "dbln",
        "value": "%7B%2261560654447805%22%3A%220WfChsf4%22%2C%2261561125998620%22%3A%22xP07py8K%22%2C%2261561903029104%22%3A%22nRuQe2aG%22%7D",
        "domain": "facebook.com",
        "path": "/login/device-based/",
        "hostOnly": false,
        "creation": "2024-07-14T06:18:17.811Z",
        "lastAccessed": "2024-07-14T06:18:17.811Z"
    },
    {
        "key": "sb",
        "value": "m_pYZuZlEOvKpW3rSxMZhcCH",
        "domain": "facebook.com",
        "path": "/",
        "hostOnly": false,
        "creation": "2024-07-14T06:18:17.812Z",
        "lastAccessed": "2024-07-14T06:18:17.812Z"
    },
    {
        "key": "m_ls",
        "value": "%7B%2261560199484370%22%3A%7B%22c%22%3A%7B%221%22%3A%22HCwAABbYBRbSqvfoARMFFqTPlJ2j_xsA%22%2C%222%22%3A%22GRwVQBxMAAAWARak6vHlDBYAFqTq8eUMABYoAA%22%2C%2295%22%3A%22HCwAABYGFvjhk4QKEwUWpM-UnaP_GwA%22%7D%2C%22d%22%3A%224e3aab26-d7b0-443f-b3e4-2409fdab8cb7%22%2C%22s%22%3A%220%22%2C%22u%22%3A%22wpl9g7%22%7D%2C%2261560280574497%22%3A%7B%22c%22%3A%7B%7D%2C%22d%22%3A%22ad58c3be-72a3-4d35-8f72-3304aee32890%22%2C%22s%22%3A%221%22%2C%22u%22%3A%22fszo24%22%7D%7D",
        "domain": "facebook.com",
        "path": "/",
        "hostOnly": false,
        "creation": "2024-07-14T06:18:17.812Z",
        "lastAccessed": "2024-07-14T06:18:17.812Z"
    },
    {
        "key": "dpr",
        "value": "3.0234789848327637",
        "domain": "facebook.com",
        "path": "/",
        "hostOnly": false,
        "creation": "2024-07-14T06:18:17.812Z",
        "lastAccessed": "2024-07-14T06:18:17.812Z"
    },
    {
        "key": "ps_n",
        "value": "1",
        "domain": "facebook.com",
        "path": "/",
        "hostOnly": false,
        "creation": "2024-07-14T06:18:17.812Z",
        "lastAccessed": "2024-07-14T06:18:17.812Z"
    },
    {
        "key": "ps_l",
        "value": "1",
        "domain": "facebook.com",
        "path": "/",
        "hostOnly": false,
        "creation": "2024-07-14T06:18:17.812Z",
        "lastAccessed": "2024-07-14T06:18:17.812Z"
    },
    {
        "key": "locale",
        "value": "ar_AR",
        "domain": "facebook.com",
        "path": "/",
        "hostOnly": false,
        "creation": "2024-07-14T06:18:17.812Z",
        "lastAccessed": "2024-07-14T06:18:17.812Z"
    },
    {
        "key": "vpd",
        "value": "v1%3B712x393x2.75",
        "domain": "facebook.com",
        "path": "/",
        "hostOnly": false,
        "creation": "2024-07-14T06:18:17.812Z",
        "lastAccessed": "2024-07-14T06:18:17.812Z"
    },
    {
        "key": "datr",
        "value": "akuTZrYvGSIq-4F2qRRDX21F",
        "domain": "facebook.com",
        "path": "/",
        "hostOnly": false,
        "creation": "2024-07-14T06:18:17.812Z",
        "lastAccessed": "2024-07-14T06:18:17.812Z"
    },
    {
        "key": "m_pixel_ratio",
        "value": "2.75",
        "domain": "facebook.com",
        "path": "/",
        "hostOnly": false,
        "creation": "2024-07-14T06:18:17.812Z",
        "lastAccessed": "2024-07-14T06:18:17.812Z"
    },
    {
        "key": "wd",
        "value": "393x712",
        "domain": "facebook.com",
        "path": "/",
        "hostOnly": false,
        "creation": "2024-07-14T06:18:17.812Z",
        "lastAccessed": "2024-07-14T06:18:17.812Z"
    },
    {
        "key": "fr",
        "value": "1HDBruNvYnXrspuHI.AWXqbhug8kKWmrWPwBJQI46xwUg.Bmk0tq..AAA.0.0.Bmk22Z.AWUxPnTKrEw",
        "domain": "facebook.com",
        "path": "/",
        "hostOnly": false,
        "creation": "2024-07-14T06:18:17.812Z",
        "lastAccessed": "2024-07-14T06:18:17.812Z"
    },
    {
        "key": "c_user",
        "value": "61561903029104",
        "domain": "facebook.com",
        "path": "/",
        "hostOnly": false,
        "creation": "2024-07-14T06:18:17.812Z",
        "lastAccessed": "2024-07-14T06:18:17.812Z"
    },
    {
        "key": "xs",
        "value": "24%3Aze4p7jaZ7BhS0g%3A2%3A1720937883%3A-1%3A-1",
        "domain": "facebook.com",
        "path": "/",
        "hostOnly": false,
        "creation": "2024-07-14T06:18:17.812Z",
        "lastAccessed": "2024-07-14T06:18:17.812Z"
    },
    {
        "key": "fbl_st",
        "value": "101335339%3BT%3A28682298",
        "domain": "facebook.com",
        "path": "/",
        "hostOnly": false,
        "creation": "2024-07-14T06:18:17.812Z",
        "lastAccessed": "2024-07-14T06:18:17.812Z"
    },
    {
        "key": "wl_cbv",
        "value": "v2%3Bclient_version%3A2561%3Btimestamp%3A1720937892",
        "domain": "facebook.com",
        "path": "/",
        "hostOnly": false,
        "creation": "2024-07-14T06:18:17.812Z",
        "lastAccessed": "2024-07-14T06:18:17.812Z"
    }
        ]
