[
    {
        "key": "sb",
        "value": "m_pYZuZlEOvKpW3rSxMZhcCH",
        "domain": "facebook.com",
        "path": "/",
        "hostOnly": false,
        "creation": "2024-06-02T10:32:33.355Z",
        "lastAccessed": "2024-06-02T10:32:33.356Z"
    },
    {
        "key": "dpr",
        "value": "3.0234789848327637",
        "domain": "facebook.com",
        "path": "/",
        "hostOnly": false,
        "creation": "2024-06-02T10:32:33.356Z",
        "lastAccessed": "2024-06-02T10:32:33.356Z"
    },
    {
        "key": "wd",
        "value": "891x1614",
        "domain": "facebook.com",
        "path": "/",
        "hostOnly": false,
        "creation": "2024-06-02T10:32:33.356Z",
        "lastAccessed": "2024-06-02T10:32:33.356Z"
    },
    {
        "key": "c_user",
        "value": "61559988465098",
        "domain": "facebook.com",
        "path": "/",
        "hostOnly": false,
        "creation": "2024-06-02T10:32:33.356Z",
        "lastAccessed": "2024-06-02T10:32:33.356Z"
    },
    {
        "key": "xs",
        "value": "46%3AJh6WRGJGZXQHKg%3A2%3A1717324121%3A-1%3A-1",
        "domain": "facebook.com",
        "path": "/",
        "hostOnly": false,
        "creation": "2024-06-02T10:32:33.356Z",
        "lastAccessed": "2024-06-02T10:32:33.356Z"
    },
    {
        "key": "fr",
        "value": "1FWv7Z9ZBGlfA1AES.AWXbuALoQwSsALF-_Ec9E7V191g.BmXElA..AAA.0.0.BmXEow.AWVdHa8wn8I",
        "domain": "facebook.com",
        "path": "/",
        "hostOnly": false,
        "creation": "2024-06-02T10:32:33.356Z",
        "lastAccessed": "2024-06-02T10:32:33.356Z"
    }
        ]
